Metadata-Version: 1.0
Name: AWS-distributions
Version: 0.1
Summary: Gaussian distributions and Binomial distributions
Home-page: UNKNOWN
Author: Sen Yang
Author-email: UNKNOWN
License: UNKNOWN
Platform: UNKNOWN
